hashkv/__init__.py
hashkv-2025.8.241553.dist-info/licenses/LICENSE
hashkv-2025.8.241553.dist-info/METADATA
hashkv-2025.8.241553.dist-info/WHEEL
hashkv-2025.8.241553.dist-info/top_level.txt
hashkv-2025.8.241553.dist-info/RECORD
